CHANGELOG.rst
README.rst
calls/__init__.py
calls/py.typed
calls-0.2.0.dist-info/WHEEL
calls-0.2.0.dist-info/METADATA
calls-0.2.0.dist-info/RECORD
